pandas_plus/__init__.py
pandas_plus/extend_pandas.py
pandas_plus/.ipynb_checkpoints/__init__-checkpoint.py
pandas_plus/.ipynb_checkpoints/extend_pandas-checkpoint.py
pandas_plus-0.0.5.dist-info/METADATA
pandas_plus-0.0.5.dist-info/WHEEL
pandas_plus-0.0.5.dist-info/licenses/LICENSE
pandas_plus-0.0.5.dist-info/RECORD
